learnml/__init__.py
learnml/impute/__init__.py
learnml/impute/_base.py
learnml/impute/tests/__init__.py
learnml/impute/tests/test_impute.py
learnml/linear_model/__init__.py
learnml/linear_model/_base.py
learnml/linear_model/_perceptron.py
learnml/linear_model/_ridge.py
learnml/linear_model/_stochastic_gradient.py
learnml/linear_model/tests/__init__.py
learnml/linear_model/tests/test_base.py
learnml/linear_model/tests/test_perceptron.py
learnml/linear_model/tests/test_ridge.py
learnml/linear_model/tests/test_sgd.py
learnml/metrics/__init__.py
learnml/metrics/classification.py
learnml/metrics/regression.py
learnml/metrics/tests/__init__.py
learnml/metrics/tests/test_classification.py
learnml/metrics/tests/test_regression.py
learnml/model_selection/__init__.py
learnml/model_selection/_split.py
learnml/model_selection/tests/__init__.py
learnml/model_selection/tests/test_split.py
learnml/neural_network/__init__.py
learnml/neural_network/_base.py
learnml/neural_network/tests/__init__.py
learnml/neural_network/tests/test_base.py
learnml/preprocessing/__init__.py
learnml/preprocessing/_data.py
learnml/preprocessing/_encoders.py
learnml/preprocessing/tests/__init__.py
learnml/preprocessing/tests/test_data.py
learnml/preprocessing/tests/test_encoders.py
learnml/tree/__init__.py
learnml/tree/tree.py
learnml/tree/tests/__init__.py
learnml/tree/tests/test_tree.py
learnml/utils/__init__.py
learnml/utils/sigmoid.py
learnml/utils/tests/__init__.py
learnml/utils/tests/test_sigmoid.py
learnml/visuals/__init__.py
learnml/visuals/stochastic_gradient.py
learnml/visuals/tree.py
learnml-0.11.1.dist-info/LICENSE
learnml-0.11.1.dist-info/METADATA
learnml-0.11.1.dist-info/WHEEL
learnml-0.11.1.dist-info/top_level.txt
learnml-0.11.1.dist-info/RECORD
