Metadata-Version: 2.1
Name: learnml
Version: 0.11.1
Summary: LearnML is a Python module for Machine Learning and Deep Learning.
Home-page: https://github.com/Vipul97/learnml
Author: Vipul Gharde
Classifier: Intended Audience :: Developers
Classifier: Intended Audience :: Science/Research
Classifier: License :: OSI Approved
Classifier: Operating System :: MacOS
Classifier: Operating System :: Microsoft :: Windows
Classifier: Operating System :: POSIX
Classifier: Operating System :: Unix
Classifier: Programming Language :: Python
Classifier: Programming Language :: Python :: 3.11
Classifier: Programming Language :: Python :: 3.12
Classifier: Topic :: Scientific/Engineering
Classifier: Topic :: Software Development
Requires-Python: >=3.11
License-File: LICENSE
Requires-Dist: graphviz
Requires-Dist: matplotlib
Requires-Dist: numpy
Requires-Dist: pandas
